pezzott_test/__init__.py
pezzott_test/_sum.py
pezzott_test-0.1.0.dist-info/METADATA
pezzott_test-0.1.0.dist-info/WHEEL
pezzott_test-0.1.0.dist-info/RECORD
