Metadata-Version: 2.3
Name: pezzott-test
Version: 0.1.0
Summary: Um pacote Python simples para teste
License: MIT
Keywords: test,exemplo,python
Author: alisonpezzott
Author-email: alisonpezzott@gmail.com
Requires-Python: >=3.8
Classifier: Development Status :: 3 - Alpha
Classifier: Intended Audience :: Developers
Classifier: License :: OSI Approved :: MIT License
Classifier: Programming Language :: Python :: 3
Classifier: Programming Language :: Python :: 3.8
Classifier: Programming Language :: Python :: 3.9
Classifier: Programming Language :: Python :: 3.10
Classifier: Programming Language :: Python :: 3.11
Classifier: Programming Language :: Python :: 3.12
